{"version":"song_preview_page_v1","song_key":"三日月","title":"三日月","charts":[{"chart":{"id":"ese:ESE-master\\ese\\01 Pop\\Mikazuki\\Mikazuki.tja::Hard","title":"三日月","display_title":"三日月","title_normalized":"三日月","course":"Hard","course_label":"困难","level":4,"bpm":72.0,"combo":171,"const":5.2,"source":"encoder","duplicate_index":1,"ese":{"category":"01 Pop","balloon_declared":null},"v4":{"stamina":0.0,"reading":0.489,"burst":0.0,"rhythm":0.6394,"complex":0.0}},"preview":{"source":"local_tja","course":"Hard","measure_count":31,"shown_measure_count":31,"is_clipped":false,"timing_version":2,"audio":{"path":"ESE-master/ese/01 Pop/Mikazuki/Mikazuki.ogg","offset":-3.532,"format":"ogg"},"measures":["0","0","0","2000200020112000","2000200020112000","2000200020112000","2000200020112000","2000200020112000","2000200020112000","2000200020112000","2000201020222000","2022202220222022","2010100010001000","2022202220222022","2010100000100100","1000201020112000","0020002000202020","1000100010222000","1000100010222000","5000000080002010","2010002000111020","1111100200111020","1111100200000000","1000100010222000","1000100010222000","5000000080002010","2010002000111020","1111100200111020","1111100200003000","3","0"],"note_count":173,"max_measure_resolution":16,"timing_summary":{"bpm_change_count":0,"scroll_change_count":0,"delay_count":0,"measure_change_count":0,"barline_off_count":0,"min_bpm":72.0,"max_bpm":72.0,"min_scroll":1.0,"max_scroll":1.0,"total_delay":0.0,"duration":103.3333,"visual_duration":124.0,"segment_measure_count":0}}},{"chart":{"id":"ese:ESE-master\\ese\\01 Pop\\Mikazuki\\Mikazuki.tja::Oni","title":"三日月","display_title":"三日月","title_normalized":"三日月","course":"Oni","course_label":"魔王","level":5,"bpm":72.0,"combo":227,"const":7.3,"source":"encoder","duplicate_index":1,"ese":{"category":"01 Pop","balloon_declared":"12"},"v4":{"stamina":0.2096,"reading":1.3537,"burst":0.0,"rhythm":1.2195,"complex":0.0}},"preview":{"source":"local_tja","course":"Oni","measure_count":30,"shown_measure_count":30,"is_clipped":false,"timing_version":2,"audio":{"path":"ESE-master/ese/01 Pop/Mikazuki/Mikazuki.ogg","offset":-3.532,"format":"ogg"},"measures":["0","0","0","2000201020112000","2020201120112220","2000201020112000","2020201020112010","2000201020112000","2020201120112220","2000201020112000","2020201020112000","2211222122112221","0110200020002000","2211212122112022","0110100000100100","1000201020212020","0020002000202020","1022102210221012","1010021010221010","500000000000000000000008000000200200200000100000","2010021000222020","1112102100212020","1112102100200200","1022102210221012","1010021010221010","7000000080222010","2010021000222020","1112102100404040","1112102100002020","0040000000000000"],"note_count":229,"max_measure_resolution":48,"timing_summary":{"bpm_change_count":0,"scroll_change_count":0,"delay_count":0,"measure_change_count":0,"barline_off_count":0,"min_bpm":72.0,"max_bpm":72.0,"min_scroll":1.0,"max_scroll":1.0,"total_delay":0.0,"duration":100.0,"visual_duration":120.0,"segment_measure_count":0}}}]}